MANIFEST.in
README.rst
setup.py
topos-previewjs.json
topos/ext/preview/__init__.py
topos/ext/preview/pmesh.py
topos/ext/preview/version.py
topos/ext/preview/widgets.py
topos/ext/preview/static/extension.js
topos/ext/preview/static/index.js
topos/ext/preview/static/index.js.map
topos_preview.egg-info/PKG-INFO
topos_preview.egg-info/SOURCES.txt
topos_preview.egg-info/dependency_links.txt
topos_preview.egg-info/not-zip-safe
topos_preview.egg-info/requires.txt
topos_preview.egg-info/top_level.txt